g/__init__.py
g/window.py
3d-0.1.1.dist-info/METADATA
3d-0.1.1.dist-info/WHEEL
3d-0.1.1.dist-info/RECORD
