Metadata-Version: 2.1
Name: 3d
Version: 0.1.1
Summary: 3D makes 3D game design easy
Author: dylanopen
Author-email: opendylan@proton.me
Requires-Python: >=3.10,<4.0
Classifier: Programming Language :: Python :: 3
Classifier: Programming Language :: Python :: 3.10
Classifier: Programming Language :: Python :: 3.11
